seeding/__init__.py
seeding/seeding.py
seeding-0.1.0.dist-info/LICENSE
seeding-0.1.0.dist-info/METADATA
seeding-0.1.0.dist-info/WHEEL
seeding-0.1.0.dist-info/top_level.txt
seeding-0.1.0.dist-info/RECORD
